facts/__init__.py
facts/arxiv.py
facts/atel.py
facts/conclude.py
facts/core.py
facts/gcn.py
facts/learn.py
facts/tools.py
literature_to_facts-0.1.0.dist-info/COPYING
literature_to_facts-0.1.0.dist-info/METADATA
literature_to_facts-0.1.0.dist-info/WHEEL
literature_to_facts-0.1.0.dist-info/entry_points.txt
literature_to_facts-0.1.0.dist-info/top_level.txt
literature_to_facts-0.1.0.dist-info/RECORD
